{
    "list": [
        {
            "title": "客户调研企业端",
            "id": 1,
            "QuestionnaireId": 272,
            "CreateDate": "2020-03-30 10:18",
            "UpdateDate": "2020-03-30 10:21",
            "IsLocked": true,
            "IsPublic": false,
            "IsClosed": false,
            "QuestionnaireType": 2,
            "IsShowGreeting": false,
            "IsAdminTop": true,
            "IsTop": true
        },
        {
            "title": "肯耐珂萨招聘服务 客户调研-企业端_20191204130318",
            "id": 2,
            "QuestionnaireId": 272,
            "CreateDate": "2020-03-30 10:18",
            "UpdateDate": "2020-03-30 10:21",
            "IsLocked": true,
            "IsPublic": false,
            "IsClosed": false,
            "QuestionnaireType": 2,
            "IsShowGreeting": false,
            "IsAdminTop": true,
            "IsTop": true
        },
        {
            "title": "题目切换正确答案问题测试",
            "id": 3,
            "QuestionnaireId": 272,
            "CreateDate": "2020-03-30 10:18",
            "UpdateDate": "2020-03-30 10:21",
            "IsLocked": true,
            "IsPublic": false,
            "IsClosed": false,
            "QuestionnaireType": 2,
            "IsShowGreeting": false,
            "IsAdminTop": true,
            "IsTop": true
        },
        {
            "title": "test002分数统计",
            "id": 4,
            "QuestionnaireId": 272,
            "CreateDate": "2020-03-30 10:18",
            "UpdateDate": "2020-03-30 10:21",
            "IsLocked": true,
            "IsPublic": false,
            "IsClosed": false,
            "QuestionnaireType": 2,
            "IsShowGreeting": false,
            "IsAdminTop": true,
            "IsTop": true
        },
        {
            "title": "test考试分数统计",
            "id": 5,
            "QuestionnaireId": 272,
            "CreateDate": "2020-03-30 10:18",
            "UpdateDate": "2020-03-30 10:21",
            "IsLocked": true,
            "IsPublic": false,
            "IsClosed": false,
            "QuestionnaireType": 2,
            "IsShowGreeting": false,
            "IsAdminTop": true,
            "IsTop": true
        },
        {
            "title": "allsplit002",
            "id": 6,
            "QuestionnaireId": 272,
            "CreateDate": "2020-03-30 10:18",
            "UpdateDate": "2020-03-30 10:21",
            "IsLocked": true,
            "IsPublic": false,
            "IsClosed": false,
            "QuestionnaireType": 2,
            "IsShowGreeting": false,
            "IsAdminTop": true,
            "IsTop": true
        },
        {
            "title": "565656",
            "id": 7,
            "QuestionnaireId": 272,
            "CreateDate": "2020-03-30 10:18",
            "UpdateDate": "2020-03-30 10:21",
            "IsLocked": true,
            "IsPublic": false,
            "IsClosed": false,
            "QuestionnaireType": 2,
            "IsShowGreeting": false,
            "IsAdminTop": true,
            "IsTop": true
        },
        {
            "title": "调研逻辑测试问卷",
            "id": 8,
            "QuestionnaireId": 272,
            "CreateDate": "2020-03-30 10:18",
            "UpdateDate": "2020-03-30 10:21",
            "IsLocked": true,
            "IsPublic": false,
            "IsClosed": false,
            "QuestionnaireType": 2,
            "IsShowGreeting": false,
            "IsAdminTop": true,
            "IsTop": true
        },
        {
            "title": "一页一题测试",
            "id": 9,
            "QuestionnaireId": 272,
            "CreateDate": "2020-03-30 10:18",
            "UpdateDate": "2020-03-30 10:21",
            "IsLocked": true,
            "IsPublic": false,
            "IsClosed": false,
            "QuestionnaireType": 2,
            "IsShowGreeting": false,
            "IsAdminTop": true,
            "IsTop": true
        },
        {
            "title": "肯耐珂萨招聘服务 客户调研-企业端_20191204130318",
            "id": 10,
            "QuestionnaireId": 272,
            "CreateDate": "2020-03-30 10:18",
            "UpdateDate": "2020-03-30 10:21",
            "IsLocked": true,
            "IsPublic": false,
            "IsClosed": false,
            "QuestionnaireType": 2,
            "IsShowGreeting": false,
            "IsAdminTop": true,
            "IsTop": true
        },
        {
            "title": "题目切换正确答案问题测试",
            "id": 11,
            "QuestionnaireId": 272,
            "CreateDate": "2020-03-30 10:18",
            "UpdateDate": "2020-03-30 10:21",
            "IsLocked": true,
            "IsPublic": false,
            "IsClosed": false,
            "QuestionnaireType": 2,
            "IsShowGreeting": false,
            "IsAdminTop": true,
            "IsTop": true
        },
        {
            "title": "test002分数统计",
            "id": 12,
            "QuestionnaireId": 272,
            "CreateDate": "2020-03-30 10:18",
            "UpdateDate": "2020-03-30 10:21",
            "IsLocked": true,
            "IsPublic": false,
            "IsClosed": false,
            "QuestionnaireType": 2,
            "IsShowGreeting": false,
            "IsAdminTop": true,
            "IsTop": true
        },
        {
            "title": "test考试分数统计",
            "id": 13,
            "QuestionnaireId": 272,
            "CreateDate": "2020-03-30 10:18",
            "UpdateDate": "2020-03-30 10:21",
            "IsLocked": true,
            "IsPublic": false,
            "IsClosed": false,
            "QuestionnaireType": 2,
            "IsShowGreeting": false,
            "IsAdminTop": true,
            "IsTop": true
        },
        {
            "title": "allsplit002",
            "id": 14,
            "QuestionnaireId": 272,
            "CreateDate": "2020-03-30 10:18",
            "UpdateDate": "2020-03-30 10:21",
            "IsLocked": true,
            "IsPublic": false,
            "IsClosed": false,
            "QuestionnaireType": 2,
            "IsShowGreeting": false,
            "IsAdminTop": true,
            "IsTop": true
        },
        {
            "title": "565656",
            "id": 15,
            "QuestionnaireId": 272,
            "CreateDate": "2020-03-30 10:18",
            "UpdateDate": "2020-03-30 10:21",
            "IsLocked": true,
            "IsPublic": false,
            "IsClosed": false,
            "QuestionnaireType": 2,
            "IsShowGreeting": false,
            "IsAdminTop": true,
            "IsTop": true
        },
        {
            "title": "调研逻辑测试问卷",
            "id": 16,
            "QuestionnaireId": 272,
            "CreateDate": "2020-03-30 10:18",
            "UpdateDate": "2020-03-30 10:21",
            "IsLocked": true,
            "IsPublic": false,
            "IsClosed": false,
            "QuestionnaireType": 2,
            "IsShowGreeting": false,
            "IsAdminTop": true,
            "IsTop": true
        },
        {
            "title": "一页一题测试",
            "id": 17,
            "QuestionnaireId": 272,
            "CreateDate": "2020-03-30 10:18",
            "UpdateDate": "2020-03-30 10:21",
            "IsLocked": true,
            "IsPublic": false,
            "IsClosed": false,
            "QuestionnaireType": 2,
            "IsShowGreeting": false,
            "IsAdminTop": true,
            "IsTop": true
        },
        {
            "title": "肯耐珂萨招聘服务 客户调研-企业端_20191204130318",
            "id": 18,
            "QuestionnaireId": 272,
            "CreateDate": "2020-03-30 10:18",
            "UpdateDate": "2020-03-30 10:21",
            "IsLocked": true,
            "IsPublic": false,
            "IsClosed": false,
            "QuestionnaireType": 2,
            "IsShowGreeting": false,
            "IsAdminTop": true,
            "IsTop": true
        },
        {
            "title": "题目切换正确答案问题测试",
            "id": 19,
            "QuestionnaireId": 272,
            "CreateDate": "2020-03-30 10:18",
            "UpdateDate": "2020-03-30 10:21",
            "IsLocked": true,
            "IsPublic": false,
            "IsClosed": false,
            "QuestionnaireType": 2,
            "IsShowGreeting": false,
            "IsAdminTop": true,
            "IsTop": true
        },
        {
            "title": "test002分数统计",
            "id": 20,
            "QuestionnaireId": 272,
            "CreateDate": "2020-03-30 10:18",
            "UpdateDate": "2020-03-30 10:21",
            "IsLocked": true,
            "IsPublic": false,
            "IsClosed": false,
            "QuestionnaireType": 2,
            "IsShowGreeting": false,
            "IsAdminTop": true,
            "IsTop": true
        },
        {
            "title": "test考试分数统计",
            "id": 21,
            "QuestionnaireId": 272,
            "CreateDate": "2020-03-30 10:18",
            "UpdateDate": "2020-03-30 10:21",
            "IsLocked": true,
            "IsPublic": false,
            "IsClosed": false,
            "QuestionnaireType": 2,
            "IsShowGreeting": false,
            "IsAdminTop": true,
            "IsTop": true
        },
        {
            "title": "allsplit002",
            "id": 22,
            "QuestionnaireId": 272,
            "CreateDate": "2020-03-30 10:18",
            "UpdateDate": "2020-03-30 10:21",
            "IsLocked": true,
            "IsPublic": false,
            "IsClosed": false,
            "QuestionnaireType": 2,
            "IsShowGreeting": false,
            "IsAdminTop": true,
            "IsTop": true
        },
        {
            "title": "565656",
            "id": 23,
            "QuestionnaireId": 272,
            "CreateDate": "2020-03-30 10:18",
            "UpdateDate": "2020-03-30 10:21",
            "IsLocked": true,
            "IsPublic": false,
            "IsClosed": false,
            "QuestionnaireType": 2,
            "IsShowGreeting": false,
            "IsAdminTop": true,
            "IsTop": true
        },
        {
            "title": "调研逻辑测试问卷",
            "id": 24,
            "QuestionnaireId": 272,
            "CreateDate": "2020-03-30 10:18",
            "UpdateDate": "2020-03-30 10:21",
            "IsLocked": true,
            "IsPublic": false,
            "IsClosed": false,
            "QuestionnaireType": 2,
            "IsShowGreeting": false,
            "IsAdminTop": true,
            "IsTop": true
        },
        {
            "title": "一页一题测试",
            "id": 25,
            "QuestionnaireId": 272,
            "CreateDate": "2020-03-30 10:18",
            "UpdateDate": "2020-03-30 10:21",
            "IsLocked": true,
            "IsPublic": false,
            "IsClosed": false,
            "QuestionnaireType": 2,
            "IsShowGreeting": false,
            "IsAdminTop": true,
            "IsTop": true
        }
    ]
}